Workbook
Name pieces: 'Exo 05 - Pièces'!$B$4:$E$53
Name clients: 'Exo 05 - Clients'!$B$6:$E$30

Sheet INFORMATIONS R2
A1: MERCI DE COMPLETER LES INFORMATIONS :
A3: Numéro étudiant :
A4: Nom de famille :
A5: Prénom :
A6: Groupe :

Sheet Exo 01
B1: VENTES PAR MAGASINS ET PAR TRIMESTRE
C3: Un employé gère un point de vente dans chacune des villes suivantes. Il est nécessaire de récompenser le meilleur.
B6: Ville | C6: Trim. 1 | D6: Trim. 2 | E6: Trim 3. | F6: Trim. 4 | G6: Total Ville | H6: Moyenne par magasin | I6: CA Min. | J6: CA Max. | K6: Part du CA
B7: St Denis | C7: 4453 | D7: 772.87674 | E7: 8085.967 | F7: 7945.0962 | G7: =SUM(C7:F7) -> 21256.94 | H7: =AVERAGE(C7:F7) -> 5314.235 | I7: =min(C7:F7) -> 772.87674 | J7: =max(C7:F7) -> 8085.967 | K7: =G7/G$17 -> 0.10918151
B8: Tampon | C8: 6927 | D8: 9756.6069 | E8: 300.05801 | F8: 7533.2235 | G8: =SUM(C8:F8) -> 24516.888 | H8: =AVERAGE(C8:F8) -> 6129.2221 | I8: =min(C8:F8) -> 300.05801 | J8: =max(C8:F8) -> 9756.6069 | K8: =G8/G$17 -> 0.1259255
B9: St Pierre | C9: 9451.0905 | D9: 4823.5968 | E9: 8207.798 | F9: 4447.9469 | G9: =SUM(C9:F9) -> 26930.432 | H9: =AVERAGE(C9:F9) -> 6732.6081 | I9: =min(C9:F9) -> 4447.9469 | J9: =max(C9:F9) -> 9451.0905 | K9: =G9/G$17 -> 0.13832213
B10: Entre Deux | C10: 8949.569 | D10: 380.3634 | E10: 212.4894 | F10: 2521.8808 | G10: =SUM(C10:F10) -> 12064.303 | H10: =AVERAGE(C10:F10) -> 3016.0756 | I10: =min(C10:F10) -> 212.4894 | J10: =max(C10:F10) -> 8949.569 | K10: =G10/G$17 -> 0.061965586
B11: St Joseph | C11: 3054.7128 | D11: 5997.7012 | E11: 86.713679 | F11: 6278.5431 | G11: =SUM(C11:F11) -> 15417.671 | H11: =AVERAGE(C11:F11) -> 3854.4177 | I11: =min(C11:F11) -> 86.713679 | J11: =max(C11:F11) -> 6278.5431 | K11: =G11/G$17 -> 0.07918941
B12: St Louis | C12: 7235.2384 | D12: 2940.0603 | E12: 9995.9137 | F12: 5531.6307 | G12: =SUM(C12:F12) -> 25702.843 | H12: =AVERAGE(C12:F12) -> 6425.7108 | I12: =min(C12:F12) -> 2940.0603 | J12: =max(C12:F12) -> 9995.9137 | K12: =G12/G$17 -> 0.13201689
B13: Cilaos | C13: 1808.5869 | D13: 7794.9596 | E13: 9961.8107 | F13: 3606.2895 | G13: =SUM(C13:F13) -> 23171.647 | H13: =AVERAGE(C13:F13) -> 5792.9117 | I13: =min(C13:F13) -> 1808.5869 | J13: =max(C13:F13) -> 9961.8107 | K13: =G13/G$17 -> 0.11901597
B14: St Philippe | C14: 5032.516 | D14: 5003.1086 | E14: 1192.636 | F14: 8541.4365 | G14: =SUM(C14:F14) -> 19769.697 | H14: =AVERAGE(C14:F14) -> 4942.4243 | I14: =min(C14:F14) -> 1192.636 | J14: =max(C14:F14) -> 8541.4365 | K14: =G14/G$17 -> 0.10154262
B15: Ste Anne | C15: 1111.485 | D15: 1557.2022 | E15: 8946.6942 | F15: 1147.2418 | G15: =SUM(C15:F15) -> 12762.623 | H15: =AVERAGE(C15:F15) -> 3190.6558 | I15: =min(C15:F15) -> 1111.485 | J15: =max(C15:F15) -> 8946.6942 | K15: =G15/G$17 -> 0.065552353
B16: Bras Panon | C16: 2725.4242 | D16: 2054.3 | E16: 944.07018 | F16: 7376.7548 | G16: =SUM(C16:F16) -> 13100.549 | H16: =AVERAGE(C16:F16) -> 3275.1373 | I16: =min(C16:F16) -> 944.07018 | J16: =max(C16:F16) -> 7376.7548 | K16: =G16/G$17 -> 0.067288035
B17: Total Trimestre : | C17: =SUM(C7:C16) -> 50748.623 | D17: =SUM(D7:D16) -> 41080.776 | E17: =SUM(E7:E16) -> 47934.151 | F17: =SUM(F7:F16) -> 54930.044 | G17: =SUM(C17:F17) -> 194693.59
B18: Vente la plus faible : | C18: =min(C7:C16) -> 1111.485 | D18: =min(D7:D16) -> 380.3634 | E18: =min(E7:E16) -> 86.713679 | F18: =min(F7:F16) -> 1147.2418
B19: Vente la plus forte : | C19: =max(C7:C16) -> 9451.0905 | D19: =max(D7:D16) -> 9756.6069 | E19: =max(E7:E16) -> 9995.9137 | F19: =max(F7:F16) -> 8541.4365
B20: Moyenne des ventes : | C20: =AVERAGE(C7:C16) -> 5074.8623 | D20: =AVERAGE(D7:D16) -> 4108.0776 | E20: =AVERAGE(E7:E16) -> 4793.4151 | F20: =AVERAGE(F7:F16) -> 5493.0044
B21: Ecart Type : | C21: =STDEV(C7:C16) -> 2955.7599 | D21: =STDEV(D7:D16) -> 3117.8938 | E21: =STDEV(E7:E16) -> 4529.3878 | F21: =STDEV(F7:F16) -> 2494.4456
C23: EXERCICE : effectuer les calculs en utilisant les bonnes formules

Sheet Exo 02
A1: Explication | B1: Valeurs ou formule
A2: Montant initial de l’emprunt : | B2: 130000
A3: Nombre d’années : | B3: 10 | D3: EXERCICE : compléter les cellules de la colonne B avec les valeurs manquantes puis effectuer le calcul en utilisant la bonne formule financière. Mettre au format monétaire les champs correspondants et afficher les taux avec deux chiffres après la virgule. J'emprunte 130000 € pendant 10 ans à un taux d'intérêt annuel constant de 5,5%. Combien dois-je rembourser tous les mois ?
A4: Taux annuel : | B4: 0.055
A5: Montant du remboursement mensuel : | B5: =PMT(B4/12 , B3*12 ,-B2,0,0) -> 1410.8416

Sheet Exo 03
A1: VARIATION DU CA
B5: 2024 | C5: 2025 | D5: Variation
A6: Janvier | B6: 56000 | C6: 65000 | D6: =(C6-B6)/B6 -> 0.16071429
A7: Février | B7: 89000 | C7: 92000 | D7: =(C7-B7)/B7 -> 0.033707865
A8: Mars | B8: 12000 | C8: 15000 | D8: =(C8-B8)/B8 -> 0.25
A9: Avril | B9: 45000 | C9: 56000 | D9: =(C9-B9)/B9 -> 0.24444444
A10: Mai | B10: 48000 | C10: 45000 | D10: =(C10-B10)/B10 -> -0.0625 | F10: EXERCICE : calculer la variation du CA
A11: Juin | B11: 56000 | C11: 58000 | D11: =(C11-B11)/B11 -> 0.035714286
A12: Juillet | B12: 78000 | C12: 82000 | D12: =(C12-B12)/B12 -> 0.051282051
A13: Août | B13: 68000 | C13: 45000 | D13: =(C13-B13)/B13 -> -0.33823529
A14: Septembre | B14: 145000 | C14: 165000 | D14: =(C14-B14)/B14 -> 0.13793103
A15: Octobre | B15: 45000 | C15: 48000 | D15: =(C15-B15)/B15 -> 0.066666667
A16: Novembre | B16: 12000 | C16: 19000 | D16: =(C16-B16)/B16 -> 0.58333333
A17: Décembre | B17: 21000 | C17: 29000 | D17: =(C17-B17)/B17 -> 0.38095238
A18: Total | B18: =SUM(B6:B17) -> 675000 | C18: =SUM(C6:C17) -> 719000 | D18: =(C18-B18)/B18 -> 0.065185185

Sheet Exo 04
A1: 2024-2025 Liste des étudiants de L3 DROIT
A2: Numéro | B2: Nom | C2: Prénom | D2: Note | E2: Admis ou Ajourné
A3: 36002965 | B3: CATIGA | C3: ORNELLA | D3: 17 | E3: =IF(D3<10,"Ajourné","Admis") -> Admis
A4: 37003113 | B4: LEFRANC | C4: LAITICIA | D4: 9 | E4: =IF(D4<10,"Ajourné","Admis") -> Ajourné
A5: 38007491 | B5: SAMY | C5: AURELIE | D5: 0 | E5: =IF(D5<10,"Ajourné","Admis") -> Ajourné | G5: EXERCICE : afficher dans la colonne E, soit "Admis", soit "Ajourné" en utilisant la fonction SI
A6: 40007912 | B6: KUMAR | C6: LAURIE | D6: 13 | E6: =IF(D6<10,"Ajourné","Admis") -> Admis
A7: 38000969 | B7: BOYER | C7: LEANE | D7: 17 | E7: =IF(D7<10,"Ajourné","Admis") -> Admis
A8: 39003903 | B8: HARITHI | C8: XAVIER | D8: 13 | E8: =IF(D8<10,"Ajourné","Admis") -> Admis
A9: 37005349 | B9: CUVELIER | C9: KISHA | D9: 5 | E9: =IF(D9<10,"Ajourné","Admis") -> Ajourné
A10: 39006003 | B10: CILLIER | C10: MICHEL | D10: 19 | E10: =IF(D10<10,"Ajourné","Admis") -> Admis
A11: 39007437 | B11: OUMAR | C11: MARIE | D11: 6 | E11: =IF(D11<10,"Ajourné","Admis") -> Ajourné
A12: 38003670 | B12: MUCY | C12: ADRIEN | D12: 2 | E12: =IF(D12<10,"Ajourné","Admis") -> Ajourné
A13: 38005645 | B13: SAUTRON | C13: RAMA | D13: 9 | E13: =IF(D13<10,"Ajourné","Admis") -> Ajourné
A14: 39000419 | B14: PERFILLON | C14: FLORANE | D14: 14 | E14: =IF(D14<10,"Ajourné","Admis") -> Admis
A15: 38002565 | B15: AINAROU-CAVERY | C15: DIANA | D15: 19 | E15: =IF(D15<10,"Ajourné","Admis") -> Admis
A16: 38000329 | B16: SAIDALI | C16: KOUSSOULMY | D16: 1 | E16: =IF(D16<10,"Ajourné","Admis") -> Ajourné
A17: 38005543 | B17: RIGAUDIN | C17: AURELIE | D17: 18 | E17: =IF(D17<10,"Ajourné","Admis") -> Admis
... A138: 38005623 | B138: LAURET | C138: FAYOUM | D138: 6 | E138: =IF(D138<10,"Ajourné","Admis") -> Ajourné

Sheet Exo 05
C1: SARL Informatique PLUS
C2: Front de Mer
C3: 97410 SAINT PIERRE | K3: EXERCICE : compléter la facture avec les bonnes formules (sierreur, recherchev, si, etc.). Les matrices ont déjà été nommées : clients et pieces Lorsqu’un client est inexistant, le message affiché sera : "Client inconnu" et pour les pièces, le message sera "Pièce inconnue" ou "Prix inconnu".
F4: =VLOOKUP($E$5,'Exo 05 - Clients'!$B$5:$E$30,2,0) -> MONSIEUR SERY HUBERT
D5: Numéro client : | E5: 5 | F5: =VLOOKUP($E$5,'Exo 05 - Clients'!$B$5:$E$30,3,0) -> 1 RUELLE DES AJONCS
F6: =VLOOKUP($E$5,'Exo 05 - Clients'!$B$5:$E$30,4,0) -> 97410 SAINT PIERRE
C9: FACTURE
F10: Saint-Pierre le | G10: 45726
C12: Réf | D12: Désignation | E12: Qté | F12: Unit. HT | G12: HT Avant remise | H12: Montant Remise | I12: HT Après remise
C13: 5 | D13: =IFERROR(VLOOKUP($C13,'Exo 05 - Pièces'!$B$3:$E$53,2,0),"Pièce inconnue") -> Graveur DVD-ROM 2x | E13: 1 | F13: =IFERROR(VLOOKUP($C13,'Exo 05 - Pièces'!$B$3:$E$53,4,0),"Prix inconnu") -> 52 | H13: =IF(ISNUMBER($F13), $F13,0) -> 52 | I13: =IF(ISNUMBER($F13), $F13,0) -> 52
C14: 30 | D14: =IFERROR(VLOOKUP($C14,'Exo 05 - Pièces'!$B$3:$E$53,2,0),"Pièce inconnue") -> Carte mère ASUS pour Intel | E14: 3 | F14: =IFERROR(VLOOKUP($C14,'Exo 05 - Pièces'!$B$3:$E$53,4,0),"Prix inconnu") -> 70 | H14: =IF(ISNUMBER($F14), $F14,0) -> 70 | I14: =IF(ISNUMBER($F14), $F14,0) -> 70
C15: 4 | D15: =IFERROR(VLOOKUP($C15,'Exo 05 - Pièces'!$B$3:$E$53,2,0),"Pièce inconnue") -> Lecteur DVD-ROM 52x | E15: 1 | F15: =IFERROR(VLOOKUP($C15,'Exo 05 - Pièces'!$B$3:$E$53,4,0),"Prix inconnu") -> 18 | H15: =IF(ISNUMBER($F15), $F15,0) -> 18 | I15: =IF(ISNUMBER($F15), $F15,0) -> 18
C16: 9 | D16: =IFERROR(VLOOKUP($C16,'Exo 05 - Pièces'!$B$3:$E$53,2,0),"Pièce inconnue") -> Ecran plat Sony 17 pouces | E16: 5 | F16: =IFERROR(VLOOKUP($C16,'Exo 05 - Pièces'!$B$3:$E$53,4,0),"Prix inconnu") -> 560 | H16: =IF(ISNUMBER($F16), $F16,0) -> 560 | I16: =IF(ISNUMBER($F16), $F16,0) -> 560
C17: 60 | D17: =IFERROR(VLOOKUP($C17,'Exo 05 - Pièces'!$B$3:$E$53,2,0),"Pièce inconnue") -> Pièce inconnue | E17: 1 | F17: =IFERROR(VLOOKUP($C17,'Exo 05 - Pièces'!$B$3:$E$53,4,0),"Prix inconnu") -> Prix inconnu | H17: =IF(ISNUMBER($F17), $F17,0) -> 0 | I17: =IF(ISNUMBER($F17), $F17,0) -> 0
C18: 7 | D18: =IFERROR(VLOOKUP($C18,'Exo 05 - Pièces'!$B$3:$E$53,2,0),"Pièce inconnue") -> Graveur DVD-ROM 8x | E18: 6 | F18: =IFERROR(VLOOKUP($C18,'Exo 05 - Pièces'!$B$3:$E$53,4,0),"Prix inconnu") -> 60 | H18: =IF(ISNUMBER($F18), $F18,0) -> 60 | I18: =IF(ISNUMBER($F18), $F18,0) -> 60
C19: 1 | D19: =IFERROR(VLOOKUP($C19,'Exo 05 - Pièces'!$B$3:$E$53,2,0),"Pièce inconnue") -> Lecteur de disquette 3,5 pouces | E19: 1 | F19: =IFERROR(VLOOKUP($C19,'Exo 05 - Pièces'!$B$3:$E$53,4,0),"Prix inconnu") -> 8 | H19: =IF(ISNUMBER($F19), $F19,0) -> 8 | I19: =IF(ISNUMBER($F19), $F19,0) -> 8
C20: 3 | D20: =IFERROR(VLOOKUP($C20,'Exo 05 - Pièces'!$B$3:$E$53,2,0),"Pièce inconnue") -> Lecteur DVD-ROM 24x | E20: 1 | F20: =IFERROR(VLOOKUP($C20,'Exo 05 - Pièces'!$B$3:$E$53,4,0),"Prix inconnu") -> 16 | H20: =IF(ISNUMBER($F20), $F20,0) -> 16 | I20: =IF(ISNUMBER($F20), $F20,0) -> 16
C21: 70 | D21: =IFERROR(VLOOKUP($C21,'Exo 05 - Pièces'!$B$3:$E$53,2,0),"Pièce inconnue") -> Pièce inconnue | E21: 10 | F21: =IFERROR(VLOOKUP($C21,'Exo 05 - Pièces'!$B$3:$E$53,4,0),"Prix inconnu") -> Prix inconnu | H21: =IF(ISNUMBER($F21), $F21,0) -> 0 | I21: =IF(ISNUMBER($F21), $F21,0) -> 0
C22: 10 | D22: =IFERROR(VLOOKUP($C22,'Exo 05 - Pièces'!$B$3:$E$53,2,0),"Pièce inconnue") -> Ecran plat Sony 19 pouces | E22: 1 | F22: =IFERROR(VLOOKUP($C22,'Exo 05 - Pièces'!$B$3:$E$53,4,0),"Prix inconnu") -> 650 | H22: =IF(ISNUMBER($F22), $F22,0) -> 650 | I22: =IF(ISNUMBER($F22), $F22,0) -> 650
C23: 11 | D23: =IFERROR(VLOOKUP($C23,'Exo 05 - Pièces'!$B$3:$E$53,2,0),"Pièce inconnue") -> Ecran cathodique Hyundai 17 pouces | E23: 1 | F23: =IFERROR(VLOOKUP($C23,'Exo 05 - Pièces'!$B$3:$E$53,4,0),"Prix inconnu") -> 120 | H23: =IF(ISNUMBER($F23), $F23,0) -> 120 | I23: =IF(ISNUMBER($F23), $F23,0) -> 120
F24: TOTAL HT : | G24: =SUM(I13:I23) -> 1554 | H24: =IF(G24>100,10%*G24,0) -> 155.4 | I24: =G24-H24 -> 1398.6
F25: TVA 8,5 % : | G25: =I24*8.5% -> 118.881
F26: Total TTC : | G26: =SUM(G24:G25) -> 1672.881
C28: La société ne pratique pas l'escompte. Les factures sont payables à réception.
C29: Les intérêts de retard seront calculés sur la base de 1,5% par mois.
C31: SI TOTAL HT EST SUPERIEUR A 100 €, UNE REMISE DE 10 % EST ACCORDEE.

Sheet Exo 05 - Pièces
B1: ETAT DES STOCKS au 15/09/04
B3: N° | C3: Désignation | D3: Quantité en stock | E3: Prix
B4: 1 | C4: Lecteur de disquette 3,5 pouces | D4: 19 | E4: 8
B5: 2 | C5: Lecteur DVD-ROM 12x | D5: 13 | E5: 15
B6: 3 | C6: Lecteur DVD-ROM 24x | D6: 90 | E6: 16
B7: 4 | C7: Lecteur DVD-ROM 52x | D7: 56 | E7: 18
B8: 5 | C8: Graveur DVD-ROM 2x | D8: 34 | E8: 52
B9: 6 | C9: Graveur DVD-ROM 4x | D9: 23 | E9: 54
B10: 7 | C10: Graveur DVD-ROM 8x | D10: 56 | E10: 60
B11: 8 | C11: Ecran plat Sony 15 pouces | D11: 45 | E11: 358
B12: 9 | C12: Ecran plat Sony 17 pouces | D12: 23 | E12: 560
B13: 10 | C13: Ecran plat Sony 19 pouces | D13: 12 | E13: 650
B14: 11 | C14: Ecran cathodique Hyundai 17 pouces | D14: 56 | E14: 120
B15: 12 | C15: Ecran cathodique Hyundai 19 pouces | D15: 89 | E15: 150
... B53: 50 | C53: Modem Olitec ADSL 512 Ko | D53: 45 | E53: 90

Sheet Exo 05 - Clients
B2: FICHIER CLIENTS
B5: Numero client | C5: Nom | D5: Adresse | E5: Code postal
B6: 1 | C6: MONSIEUR TEXIPPR | D6: 1 AVENUE JEAN JAURES | E6: 97430 TAMPON
B7: 2 | C7: MONSIEUR TURPIN | D7: 1 AVENUE JEAN MALOT | E7: 97430 TAMPON
B8: 3 | C8: MONSIEUR SIMJEE | D8: 1 CHEMIN FERRERE | E8: 97410 SAINT PIERRE
B9: 4 | C9: MONSIEUR SIMANS JEAN | D9: 1 RUE DU DOCTEUR MANES | E9: 97414 ENTRE-DEUX
B10: 5 | C10: MONSIEUR SERY HUBERT | D10: 1 RUELLE DES AJONCS | E10: 97410 SAINT PIERRE
B11: 6 | C11: MONSIEUR SALAMBO JEAN | D11: 10 BIS RTE NATIONALE PIERREFONDS | E11: 97410 SAINT PIERRE
B12: 7 | C12: MONSIEUR SADEHE | D12: 10 BIS RTE NATIONALE | E12: 97480 SAINT JOSEPH
B13: 8 | C13: MONSIEUR ROUCOU | D13: 10 CHEMIN ACQUIER | E13: 97414 ENTRE-DEUX
B14: 9 | C14: MONSIEUR ROSSOLIN | D14: 10 RUE JEAN ALBANY | E14: 97414 ENTRE-DEUX
B15: 10 | C15: MONSIEUR ROBERT LOUIS | D15: 10 RUELLE DES FRERES | E15: 97410 SAINT PIERRE
B16: 11 | C16: MONSIEUR RIVIERE PAUL | D16: 11 RUE DU SOUFFLEUR | E16: 97427 ETANG-SALE
B17: 12 | C17: MONSIEUR RIVIERE LUCO | D17: 11 RUELLE MARIE ESTELLA | E17: 97480 SAINT JOSEPH
... B30: 25 | C30: MONSIEUR MARI | D30: 17 RUE PAUL HERMANN | E30: 97414 ENTRE-DEUX
